inmanta_sphinx-0.3-py3.5-nspkg.pth
inmanta_sphinx-0.3.dist-info/DESCRIPTION.rst
inmanta_sphinx-0.3.dist-info/METADATA
inmanta_sphinx-0.3.dist-info/RECORD
inmanta_sphinx-0.3.dist-info/WHEEL
inmanta_sphinx-0.3.dist-info/entry_points.txt
inmanta_sphinx-0.3.dist-info/metadata.json
inmanta_sphinx-0.3.dist-info/namespace_packages.txt
inmanta_sphinx-0.3.dist-info/top_level.txt
sphinxcontrib/inmanta/__init__.py
sphinxcontrib/inmanta/api.py
sphinxcontrib/inmanta/config.py
sphinxcontrib/inmanta/dsl.py
sphinxcontrib/inmanta/pygments_lexer.py
