Metadata-Version: 2.0
Name: inmanta-sphinx
Version: 0.3
Summary: Jinja domain for jinja templates
Home-page: https://github.com/inmanta/sphinxcontrib.jinjadomain
Author: Inmanta
Author-email: code@inmanta.com
License: ASL 2.0
Platform: any
Classifier: Development Status :: 4 - Beta
Classifier: Environment :: Console
Classifier: Environment :: Web Environment
Classifier: Intended Audience :: Developers
Classifier: License :: OSI Approved :: BSD License
Classifier: Operating System :: OS Independent
Classifier: Programming Language :: Python
Classifier: Topic :: Documentation
Classifier: Topic :: Utilities
Requires-Dist: Sphinx (>=1.5)
Requires-Dist: click
